django_ui_forms/__init__.py
django_ui_forms/forms.py
django_ui_forms/models.py
django_ui_forms/templates/bootstrap_forms_snippet.html
django_ui_forms/templates/tailwind_forms_snippet.html
django_ui_forms/templates/django/forms/attrs.html
django_ui_forms/templates/django/forms/div.html
django_ui_forms/templates/django/forms/field.html
django_ui_forms/templates/django/forms/label.html
django_ui_forms/templates/django/forms/p.html
django_ui_forms/templates/django/forms/table.html
django_ui_forms/templates/django/forms/ul.html
django_ui_forms/templates/django/forms/errors/dict/default.html
django_ui_forms/templates/django/forms/errors/dict/text.txt
django_ui_forms/templates/django/forms/errors/dict/ul.html
django_ui_forms/templates/django/forms/errors/list/default.html
django_ui_forms/templates/django/forms/errors/list/text.txt
django_ui_forms/templates/django/forms/errors/list/ul.html
django_ui_forms/templates/django/forms/formsets/div.html
django_ui_forms/templates/django/forms/formsets/p.html
django_ui_forms/templates/django/forms/formsets/table.html
django_ui_forms/templates/django/forms/formsets/ul.html
django_ui_forms/templates/django/forms/widgets/attrs.html
django_ui_forms/templates/django/forms/widgets/checkbox.html
django_ui_forms/templates/django/forms/widgets/checkbox_option.html
django_ui_forms/templates/django/forms/widgets/checkbox_select.html
django_ui_forms/templates/django/forms/widgets/clearable_file_input.html
django_ui_forms/templates/django/forms/widgets/date.html
django_ui_forms/templates/django/forms/widgets/datetime.html
django_ui_forms/templates/django/forms/widgets/email.html
django_ui_forms/templates/django/forms/widgets/file.html
django_ui_forms/templates/django/forms/widgets/hidden.html
django_ui_forms/templates/django/forms/widgets/input.html
django_ui_forms/templates/django/forms/widgets/input_option.html
django_ui_forms/templates/django/forms/widgets/multiple_hidden.html
django_ui_forms/templates/django/forms/widgets/multiple_input.html
django_ui_forms-1.1.dist-info/LICENSE
django_ui_forms-1.1.dist-info/METADATA
django_ui_forms-1.1.dist-info/WHEEL
django_ui_forms-1.1.dist-info/top_level.txt
django_ui_forms-1.1.dist-info/RECORD
