Metadata-Version: 2.1
Name: django-ui-forms
Version: 1.1
Summary: A Django reusable app to extend forms with Bootstrap and Tailwind CSS support
Home-page: https://github.com/mohitprajapat2001/django-ui-forms
Author: Mohit Prajapat
Author-email: mohitdevelopment2001@gmail.com
Classifier: Framework :: Django
Classifier: Intended Audience :: Developers
Classifier: License :: OSI Approved :: MIT License
Classifier: Operating System :: OS Independent
Classifier: Programming Language :: Python :: 3
Classifier: Programming Language :: Python :: 3.8
Classifier: Programming Language :: Python :: 3.9
Classifier: Programming Language :: Python :: 3.10
Classifier: Programming Language :: Python :: 3.11
License-File: LICENSE
Requires-Dist: django>=5.1
